cptool_py/UI.py
cptool_py/__init__.py
cptool_py/args.py
cptool_py/commands.py
cptool_py/cp_tool.py
cptool_py/error.py
cptool_py/fileio.py
cptool_py/formatting.py
cptool_py/template.py
cptool_py-2.0.5.dist-info/licenses/LICENSE
cptool_py-2.0.5.dist-info/METADATA
cptool_py-2.0.5.dist-info/WHEEL
cptool_py-2.0.5.dist-info/entry_points.txt
cptool_py-2.0.5.dist-info/top_level.txt
cptool_py-2.0.5.dist-info/RECORD
