Metadata-Version: 2.4
Name: cptool-py
Version: 2.0.5
Summary: CLI for creating competitive programming problem files
Author-email: Simon Ashton <simon@smntic.dev>
License: MIT
Project-URL: Homepage, https://github.com/smntic/cp-tool
Classifier: Programming Language :: Python :: 3
Classifier: License :: OSI Approved :: MIT License
Classifier: Operating System :: POSIX
Requires-Python: >=3.8
License-File: LICENSE
Requires-Dist: platformdirs
Dynamic: license-file
